<annotation>
	<folder>green</folder>
	<filename>left18166.jpg</filename>
	<path>/media/michal/DawneF5/AI_NEURAL_NETWORKS_PYTHON_UDACITY/UDACITY_MY_CAR_NANO_DEGREE/Capstone/SELECTED/green/left18166.jpg</path>
	<source>
		<database>Unknown</database>
	</source>
	<size>
		<width>800</width>
		<height>600</height>
		<depth>3</depth>
	</size>
	<segmented>0</segmented>
	<object>
		<name>green</name>
		<pose>Unspecified</pose>
		<truncated>0</truncated>
		<difficult>0</difficult>
		<bndbox>
			<xmin>134</xmin>
			<ymin>276</ymin>
			<xmax>182</xmax>
			<ymax>409</ymax>
		</bndbox>
	</object>
	<object>
		<name>green</name>
		<pose>Unspecified</pose>
		<truncated>0</truncated>
		<difficult>0</difficult>
		<bndbox>
			<xmin>363</xmin>
			<ymin>285</ymin>
			<xmax>426</xmax>
			<ymax>410</ymax>
		</bndbox>
	</object>
	<object>
		<name>green</name>
		<pose>Unspecified</pose>
		<truncated>0</truncated>
		<difficult>0</difficult>
		<bndbox>
			<xmin>600</xmin>
			<ymin>283</ymin>
			<xmax>669</xmax>
			<ymax>411</ymax>
		</bndbox>
	</object>
</annotation>
